roitools/__init__.py
roitools/__main__.py
roitools/utils.py
roitools-0.0.1.dist-info/METADATA
roitools-0.0.1.dist-info/WHEEL
roitools-0.0.1.dist-info/top_level.txt
roitools-0.0.1.dist-info/RECORD
