Metadata-Version: 2.1
Name: roitools
Version: 0.0.1
Requires-Dist: requests
